exchangerate/__init__.py
exchangerate/client.py
exchangerate/exceptions.py
exchangerate_client-0.3.0.dist-info/licenses/LICENSE
exchangerate_client-0.3.0.dist-info/METADATA
exchangerate_client-0.3.0.dist-info/WHEEL
exchangerate_client-0.3.0.dist-info/top_level.txt
exchangerate_client-0.3.0.dist-info/RECORD
