Metadata-Version: 2.4
Name: exchangerate-client
Version: 0.3.0
Summary: Unofficial exchangerate.host python client library
Home-page: https://github.com/dannyp11/exchangerate-python-client
Author: Daniel Pham
Author-email: tdpham1105@yahoo.com
Project-URL: Documentation, https://github.com/dannyp11/exchangerate-python-client
Project-URL: Bug Reports, https://github.com/dannyp11/exchangerate-python-client/issues
Project-URL: Source Code, https://github.com/dannyp11/exchangerate-python-client
Keywords: exchangerate.host,exchangerate,client
Classifier: Development Status :: 5 - Production/Stable
Classifier: Intended Audience :: Developers
Classifier: Topic :: Software Development :: Build Tools
Classifier: Programming Language :: Python :: 3
Classifier: Programming Language :: Python :: 3.6
Classifier: Programming Language :: Python :: 3.7
Classifier: Programming Language :: Python :: 3.8
Classifier: Programming Language :: Python :: 3.9
Classifier: Programming Language :: Python :: 3 :: Only
Classifier: License :: OSI Approved :: MIT License
Classifier: Operating System :: OS Independent
Requires-Python: >=3.6
License-File: LICENSE
Requires-Dist: requests
Provides-Extra: dev
Requires-Dist: check-manifest; extra == "dev"
Dynamic: author
Dynamic: author-email
Dynamic: classifier
Dynamic: description
Dynamic: description-content-type
Dynamic: home-page
Dynamic: keywords
Dynamic: license-file
Dynamic: project-url
Dynamic: provides-extra
Dynamic: requires-dist
Dynamic: requires-python
Dynamic: summary
